pyply/__init__.py
pyply/pyply.py
pyply-0.1.6.dist-info/DESCRIPTION.rst
pyply-0.1.6.dist-info/METADATA
pyply-0.1.6.dist-info/RECORD
pyply-0.1.6.dist-info/WHEEL
pyply-0.1.6.dist-info/metadata.json
pyply-0.1.6.dist-info/top_level.txt
