Metadata-Version: 2.0
Name: pyply
Version: 0.1.6
Summary: Based largely off functions found in R, pyply provides syntax in a functional programming style to make data manipulation easier.
Home-page: http://theautomatic.net/pyply-documentation/
Author: Andrew Treadway
Author-email: opensourcecoder11@gmail.com
License: UNKNOWN
Platform: UNKNOWN
